tutormailpit/__about__.py
tutormailpit/__init__.py
tutormailpit/plugin.py
tutormailpit/patches/local-docker-compose-dev-services
tutormailpit/patches/openedx-development-settings
tutor_contrib_mailpit-0.1.3.dist-info/LICENSE.txt
tutor_contrib_mailpit-0.1.3.dist-info/METADATA
tutor_contrib_mailpit-0.1.3.dist-info/WHEEL
tutor_contrib_mailpit-0.1.3.dist-info/entry_points.txt
tutor_contrib_mailpit-0.1.3.dist-info/top_level.txt
tutor_contrib_mailpit-0.1.3.dist-info/RECORD
