Metadata-Version: 2.1
Name: tutor-contrib-mailpit
Version: 0.1.3
Summary: A Tutor plugin for local email testing
Author: Abstract-Technology GmbH
Author-email: support@abstract-technology.de
Maintainer: Illia Shestakov
Maintainer-email: i.shestakov@abstract-technology.de
License: AGPLv3
Classifier: Development Status :: 5 - Production/Stable
Classifier: Intended Audience :: Developers
Classifier: License :: OSI Approved :: GNU Affero General Public License v3
Classifier: Operating System :: OS Independent
Classifier: Programming Language :: Python
Classifier: Programming Language :: Python :: 3.8
Classifier: Programming Language :: Python :: 3.9
Classifier: Programming Language :: Python :: 3.10
Classifier: Programming Language :: Python :: 3.11
Classifier: Programming Language :: Python :: 3.12
Requires-Python: >=3.8
License-File: LICENSE.txt
Requires-Dist: tutor<19.0.0,>=14.0.0
